{
  "slow-stories": {
    "title": "On Slow Stories",
    "meta": "March 2025",
    "date": "2025-03-01",
    "contentFile": "posts/slow-stories.html",
    "excerpt": "Some stories don’t want to be rushed. They unfold in pauses, in atmosphere, in what’s left unsaid."
  },
  "quiet-worlds": {
    "title": "Building Quiet Worlds",
    "meta": "February 2025",
    "date": "2025-02-15",
    "contentFile": "posts/quiet-worlds.html",
    "excerpt": "Worldbuilding doesn’t always need maps and lore. Sometimes it lives in tone, habit, and silence."
  },
  "the-hard-line-in-the-sand": {
    "title": "The Hard Line in the Sand",
    "meta": "January 2026",
    "date": "2026-01-09",
    "contentFile": "posts/the-hard-line-in-the-sand.html",
    "excerpt": "Everyone has something they won’t compromise on."
  }
}
